dpdcyconfusion/pre_install.py
dpdcyconfusion-0.1.dist-info/LICENSE.txt
dpdcyconfusion-0.1.dist-info/METADATA
dpdcyconfusion-0.1.dist-info/WHEEL
dpdcyconfusion-0.1.dist-info/top_level.txt
dpdcyconfusion-0.1.dist-info/RECORD
