Metadata-Version: 2.1
Name: dpdcyconfusion
Version: 0.1
Summary: A description of your package
Home-page: https://your.package.url
Author: dhxnush.ravi
Author-email: your.email@example.com
Classifier: Programming Language :: Python :: 3
Classifier: License :: OSI Approved :: MIT License
Classifier: Operating System :: OS Independent
Requires-Python: >=3.6
License-File: LICENSE.txt
